.gitignore
CHANGELOG.md
flatpages_tinymce/__init__.py
flatpages_tinymce/admin.py
flatpages_tinymce/settings.py
flatpages_tinymce/static/flatpages_tinymce/edit-min.css
flatpages_tinymce/static/flatpages_tinymce/edit-min.js
flatpages_tinymce/static/flatpages_tinymce/edit.css
flatpages_tinymce/static/flatpages_tinymce/edit.js
flatpages_tinymce/templates/flatpages_tinymce/_contentedit.htm
flatpages_tinymce/templatetags/__init__.py
flatpages_tinymce/templatetags/flatpage_admin.py
django3_flatpages_tinymce-0.2.2.dist-info/WHEEL
django3_flatpages_tinymce-0.2.2.dist-info/METADATA
django3_flatpages_tinymce-0.2.2.dist-info/RECORD
