Metadata-Version: 2.1
Name: django3-flatpages-tinymce
Version: 0.2.2
Summary: HTML editor on django.contrib.flatpages
Home-page: https://gitlab.com/lansharkconsulting/django/django3-flatpages-tinymce
License: MIT
Keywords: django,flatpages,tinymce,WYSIWYG
Author: Scott Sharkey
Author-email: ssharkey@lanshark.com
Requires-Python: >=3.7,<4.0
Classifier: Development Status :: 5 - Production/Stable
Classifier: Environment :: Web Environment
Classifier: Framework :: Django
Classifier: Framework :: Django :: 3.0
Classifier: Framework :: Django :: 3.1
Classifier: Framework :: Django :: 3.2
Classifier: Framework :: Django :: 4.0
Classifier: Intended Audience :: Developers
Classifier: License :: OSI Approved :: MIT License
Classifier: Natural Language :: English
Classifier: Operating System :: OS Independent
Classifier: Operating System :: POSIX
Classifier: Operating System :: Unix
Classifier: Programming Language :: Python
Classifier: Programming Language :: Python :: 3
Classifier: Programming Language :: Python :: 3.10
Classifier: Programming Language :: Python :: 3.7
Classifier: Programming Language :: Python :: 3.8
Classifier: Programming Language :: Python :: 3.9
Classifier: Topic :: Internet :: WWW/HTTP
Classifier: Topic :: Internet :: WWW/HTTP :: Dynamic Content
Classifier: Topic :: Internet :: WWW/HTTP :: Site Management
Requires-Dist: Django (>=3.0)
Requires-Dist: django_tinymce (>=1.5)
Project-URL: Repository, https://gitlab.com/lansharkconsulting/django/django3-flatpages-tinymce
